README.md
setup.py
karel/KarelForSynthesisParser_parsetab.py
karel/KarelWithCurlyParser_parsetab.py
karel/__init__.py
karel/hero.py
karel/karel.py
karel/parser_base.py
karel/parser_for_synthesis.py
karel/parser_with_curly.py
karel/utils.py
karel/yacc.py
karel.egg-info/PKG-INFO
karel.egg-info/SOURCES.txt
karel.egg-info/dependency_links.txt
karel.egg-info/requires.txt
karel.egg-info/top_level.txt
karel.egg-info/zip-safe